pendo/__init__.py
pendo/auth.py
pendo/const.py
pendo/exc.py
pendo/main.py
pendo/py.typed
pendo/types.py
pendo-0.0.5.dist-info/LICENSE
pendo-0.0.5.dist-info/WHEEL
pendo-0.0.5.dist-info/METADATA
pendo-0.0.5.dist-info/RECORD
